liver_seg/__init__.py
liver_seg/datasets/__init__.py
liver_seg/datasets/data_loader.py
liver_seg/datasets/torch_data.py
liver_seg/datasets/transforms.py
liver_seg/models/__init__.py
liver_seg/models/fpn.py
liver_seg/models/loss_funs.py
liver_seg/models/model_loader.py
liver_seg/utils/__init__.py
liver_seg/utils/visualize.py
liver_seg-0.0.2.dist-info/METADATA
liver_seg-0.0.2.dist-info/WHEEL
liver_seg-0.0.2.dist-info/top_level.txt
liver_seg-0.0.2.dist-info/RECORD
